{
  "component": {
    "sizing": {
      "button": {
        "l": {
          "value": "{alias.sizing.size-l}",
          "type": "sizing"
        }
      }
    },
    "color": {
      "button": {
        "background-color": {
          "value": "{alias.color.fill.primary-red}",
          "type": "color"
        },
        "text-color": {
          "value": "{alias.color.text.white}",
          "type": "color"
        }
      },
      "button2": {
        "background-color": {
          "value": "{alias.color.fill.green}",
          "type": "color"
        }
      }
    },
    "spacing": {
      "body": {
        "pagePaddingLR": {
          "value": "{alias.spacing.space-l}",
          "type": "spacing"
        },
        "lastBtn-padding": {
          "value": "{alias.spacing.xxxxl}",
          "type": "spacing"
        }
      }
    },
    "borderRadius": {
      "button": {
        "value": "{alias.borderRadius.button}",
        "type": "borderRadius"
      }
    },
    "typography": {
      "button": {
        "l": {
          "fontFamily": {
            "value": "{alias.typography.body.regular.fontFamily}"
          },
          "fontWeight": {
            "value": "{alias.typography.body.regular.fontWeight}"
          },
          "lineHeight": {
            "value": "{alias.typography.body.regular.lineHeight}"
          },
          "fontSize": {
            "value": "{alias.typography.body.regular.fontSize}"
          },
          "letterSpacing": {
            "value": "{alias.typography.body.regular.letterSpacing}"
          }
        }
      }
    },
    "textCase": {
      "title": {
        "value": "{alias.textCase.title}",
        "type": "textCase"
      }
    }
  }
}
